[
  {
    "name": "颂赞诗歌",
    "channel": [
      {
        "name": "505版",
        "playlist": []
      },
      {
        "name": "707版",
        "playlist": []
      },
      {
        "name": "英文诗歌",
        "playlist": [
          {
            "name": "ONCE TO EVERY MAN AND NATION"
          }
        ]
      }
    ]
  },
  {
    "name": "圣经朗读",
    "channel": [
      {
        "name": "和合本",
        "playlist": []
      },
      {
        "name": "KJV",
        "playlist": []
      },
      {
        "name": "KJV EN",
        "playlist": []
      }
    ]
  },
  {
    "name": "怀著朗读",
    "channel": [
      {
        "name": "先祖与先知",
        "playlist": []
      }
    ]
  },
  {
    "name": "朱牧讲道",
    "channel": [
      {
        "name": "儿童短讲",
        "playlist": [
          {
            "name": "天地之间有一个你"
          },
          {
            "name": "白天黑夜两个光体"
          },
          {
            "name": "古往今来地貌巨变"
          },
          {
            "name": "挪亚方舟告诉我们"
          },
          {
            "name": "地上鲜花天上彩虹"
          },
          {
            "name": "各国各语中国中文"
          },
          {
            "name": "五谷杂粮蔬菜水果"
          },
          {
            "name": "亚伯拉罕以撒雅各"
          },
          {
            "name": "预言期满的那一天"
          },
          {
            "name": "没鼻子狮身人面像"
          },
          {
            "name": "人类历史年代估算"
          },
          {
            "name": "失落的约柜何时归"
          },
          {
            "name": "过年习俗从何而来"
          },
          {
            "name": "耶和华是医治你的"
          },
          {
            "name": "全人健康八大要素"
          },
          {
            "name": "磐石穴中向主祷告"
          },
          {
            "name": "水雾雨露冰霜雪雹"
          },
          {
            "name": "可以存活永远存活"
          },
          {
            "name": "过约旦河攻耶利哥"
          },
          {
            "name": "要走世人必走的路"
          },
          {
            "name": "你呼唤我我在这里"
          },
          {
            "name": "以利和他两个儿子"
          },
          {
            "name": "今日为证愿他为证"
          },
          {
            "name": "谁想飘摇众树之上"
          }
        ]
      },
      {
        "name": "十诫专题",
        "playlist": [
          {
            "name": "爱与十诫"
          },
          {
            "name": "罪与十诫"
          },
          {
            "name": "信与十诫"
          },
          {
            "name": "约与十诫"
          },
          {
            "name": "印与十诫(上)"
          },
          {
            "name": "印与十诫(下)"
          },
          {
            "name": "十架与十诫"
          },
          {
            "name": "圣灵与十诫"
          }
        ]
      },
      {
        "name": "洁净心灵",
        "playlist": [
          {
            "name": "品格与道德机能"
          },
          {
            "name": "罪的嗜好与得胜秘诀"
          },
          {
            "name": "私欲与灵魂争战"
          },
          {
            "name": "信十字架而得生"
          },
          {
            "name": "四讲的概述"
          },
          {
            "name": "开我们的心窍"
          },
          {
            "name": "品格的罪与义"
          },
          {
            "name": "道成肉身与肉身成道"
          },
          {
            "name": "注目基督跟随基督"
          },
          {
            "name": "上帝的国在我们心里"
          },
          {
            "name": "内心的洁净"
          },
          {
            "name": "信心与意志的运用"
          },
          {
            "name": "饶恕人与被饶恕"
          },
          {
            "name": "舍己与献己"
          },
          {
            "name": "圣洁从基督而来"
          },
          {
            "name": "圣餐礼勉言1_洗净私欲"
          },
          {
            "name": "圣餐礼勉言2_不要吃喝自己的罪"
          },
          {
            "name": "除污秽的水"
          },
          {
            "name": "敬虔的奥秘"
          },
          {
            "name": "必须明白的"
          }
        ]
      },
      {
        "name": "圣经刚要",
        "playlist": [
          {
            "name": "谁会明白圣经"
          },
          {
            "name": "创世之初"
          },
          {
            "name": "善恶之争简史"
          },
          {
            "name": "耶稣得国的计划"
          },
          {
            "name": "基督是圣经的中心"
          },
          {
            "name": "十字架的福音_堕落与救赎"
          },
          {
            "name": "永约的历史"
          },
          {
            "name": "贯彻救恩的圣灵"
          },
          {
            "name": "灵魂与招魂术"
          },
          {
            "name": "安息日与兽的印记"
          },
          {
            "name": "大像与七头十角兽"
          },
          {
            "name": "怎样获得无罪的品格(上)"
          },
          {
            "name": "怎样获得无罪的品格(下)"
          },
          {
            "name": "贯穿始终的慈绳爱索"
          },
          {
            "name": "非人手凿出来的石头"
          },
          {
            "name": "展望晚雨沛降"
          },
          {
            "name": "跨越信仰上的障碍"
          },
          {
            "name": "17讲概述"
          }
        ]
      },
      {
        "name": "在疗养院",
        "playlist": [
          {
            "name": "灵性的医治"
          },
          {
            "name": "感恩带来医治"
          },
          {
            "name": "耶和华是医治我们的"
          },
          {
            "name": "生命在血液中"
          },
          {
            "name": "患难是祝福"
          },
          {
            "name": "真实的认罪"
          },
          {
            "name": "土浅石头地"
          },
          {
            "name": "人生就是训练"
          },
          {
            "name": "思想与行动"
          },
          {
            "name": "塑造品格的意义"
          }
        ]
      },
      {
        "name": "青年婚姻",
        "playlist": [
          {
            "name": "青年呼召"
          },
          {
            "name": "青年勉言"
          },
          {
            "name": "心志与目标"
          },
          {
            "name": "自修求进(上)"
          },
          {
            "name": "自修求进(下)"
          },
          {
            "name": "祈祷与献身"
          },
          {
            "name": "唯一的保障"
          },
          {
            "name": "真理与谬道根本的差异"
          },
          {
            "name": "心思的训练"
          },
          {
            "name": "预言学习七点"
          },
          {
            "name": "圣经学习七点"
          },
          {
            "name": "婚姻勉言"
          },
          {
            "name": "婚礼勉言1"
          },
          {
            "name": "婚礼勉言2"
          },
          {
            "name": "婚礼勉言3"
          }
        ]
      },
      {
        "name": "单篇分享",
        "playlist": [
          {
            "name": "伊甸园的回声"
          },
          {
            "name": "从逾越节到西奈山(十字架到十诫)"
          },
          {
            "name": "知道所当走的路"
          },
          {
            "name": "现今的写照"
          },
          {
            "name": "哀哉扫罗"
          },
          {
            "name": "大卫的心声_诗篇51篇"
          },
          {
            "name": "大卫与拔示巴"
          },
          {
            "name": "义人的口"
          },
          {
            "name": "《哈巴谷书》讲解"
          },
          {
            "name": "《撒迦利亚书》讲解"
          },
          {
            "name": "隐含的福音"
          },
          {
            "name": "创始成终"
          },
          {
            "name": "靠着鬼王赶鬼"
          },
          {
            "name": "近来“先知”挺多的"
          },
          {
            "name": "如何应对阴历安息日等谬道"
          },
          {
            "name": "走出迷茫"
          },
          {
            "name": "疑恨的条例"
          },
          {
            "name": "合乎中道的爱"
          },
          {
            "name": "与罪断绝的兵器(彼得前书)"
          },
          {
            "name": "自隐的上帝"
          },
          {
            "name": "把里面的施舍给人"
          },
          {
            "name": "罪的咒诅"
          },
          {
            "name": "脱鞋之家"
          },
          {
            "name": "如何检验自己的信仰"
          },
          {
            "name": "恩门会提前关闭吗"
          },
          {
            "name": "卖衣买刀"
          }
        ]
      },
      {
        "name": "耶稣生平",
        "playlist": [
          {
            "name": "基督当生在何处"
          },
          {
            "name": "是兴起还是毁谤"
          },
          {
            "name": "救主受到的“礼遇”"
          },
          {
            "name": "如何来得胜试探"
          },
          {
            "name": "觉察救主的同在"
          },
          {
            "name": "洁净圣殿论重生"
          },
          {
            "name": "必早求也必早给"
          },
          {
            "name": "属灵的恩典之国"
          },
          {
            "name": "是渴慕还是敌意"
          },
          {
            "name": "天国大宪章之一"
          },
          {
            "name": "天国大宪章之二"
          },
          {
            "name": "天国大宪章之三"
          },
          {
            "name": "在基督里得安息"
          },
          {
            "name": "谁是基督一家人"
          },
          {
            "name": "最初的几个比喻"
          },
          {
            "name": "使人得救的信心"
          },
          {
            "name": "给传道者的证言"
          },
          {
            "name": "信心生发的奇迹"
          },
          {
            "name": "什么是永生之道"
          },
          {
            "name": "防备伪善者的酵"
          },
          {
            "name": "背负十架的意义"
          },
          {
            "name": "如何践行十字架"
          },
          {
            "name": "议论纷纷为哪般"
          },
          {
            "name": "好牧人为羊舍命"
          },
          {
            "name": "良善撒玛利亚人"
          },
          {
            "name": "把里面的施舍人"
          },
          {
            "name": "浪子回头金不换"
          },
          {
            "name": "上帝的国在心里"
          },
          {
            "name": "是否还缺少一件"
          }
        ]
      },
      {
        "name": "但以理书讲座",
        "playlist": [
          {
            "name": "巴比伦之囚"
          },
          {
            "name": "宫廷中的俘虏"
          },
          {
            "name": "梦中的大像"
          },
          {
            "name": "在烈火的窑中"
          },
          {
            "name": "尼布甲尼撒王和他的孙子"
          },
          {
            "name": "在狮子坑中"
          },
          {
            "name": "四个大兽和小角"
          },
          {
            "name": "开始审判的时候"
          },
          {
            "name": "圣经中最长的预言"
          },
          {
            "name": "南方王和北方王"
          },
          {
            "name": "末时的争战"
          },
          {
            "name": "米迦勒站起来的时候"
          }
        ]
      },
      {
        "name": "启示录讲座",
        "playlist": [
          {
            "name": "第1章：概论"
          },
          {
            "name": "第2章：七教会（上）"
          },
          {
            "name": "第2-3章：七教会（下）"
          },
          {
            "name": "第4-5章：上帝宝座前的审判"
          },
          {
            "name": "第6章：七印（上）"
          },
          {
            "name": "第6-8章： 七印（下）"
          },
          {
            "name": "第7章：永生上帝的印"
          },
          {
            "name": "第8-11章：七号（上）"
          },
          {
            "name": "10章：展开的小书卷和上帝的奥秘"
          },
          {
            "name": "第11章：圣经与法国革命"
          },
          {
            "name": "上帝审判的时期"
          },
          {
            "name": "第12章：末时代上帝的真教会"
          },
          {
            "name": "第13章：兽的真相（上）"
          },
          {
            "name": "第13章：兽的真相（下）"
          },
          {
            "name": "第13章：兽像（上）"
          },
          {
            "name": "第13章：兽像（下）"
          },
          {
            "name": "第14章：十四万四千人"
          },
          {
            "name": "第14章：三位天使的信息"
          },
          {
            "name": "第8-14章：七号（下）"
          },
          {
            "name": "第15-16章：末了的七灾"
          },
          {
            "name": "第17-18章：巴比伦的沉沦"
          },
          {
            "name": "第19-20章：大君荣临和千禧年"
          },
          {
            "name": "第21-22章：新天新地"
          }
        ]
      },
      {
        "name": "但以理书思考",
        "playlist": [
          {
            "name": "在危机中脱颖而出的余民(1章)"
          },
          {
            "name": "上帝使用余民的理由(2章上)"
          },
          {
            "name": "末时代余民的定位石(2章下)"
          },
          {
            "name": "启示录中兽印的预演(3章)"
          },
          {
            "name": "让我们共同见证(4章)"
          },
          {
            "name": "目击巴比伦的灭亡(5章)"
          },
          {
            "name": "能站立到最后的人(6章)"
          },
          {
            "name": "善恶之争交织的历史(7章)"
          },
          {
            "name": "基督与敌基督(8章)"
          },
          {
            "name": "基督与敌基督(9章)"
          },
          {
            "name": "大争战(10章)"
          },
          {
            "name": "大争战(11章综述)"
          },
          {
            "name": "大争战(11章1-14)"
          },
          {
            "name": "大争战(11章15-30)"
          },
          {
            "name": "大争战(11章31-39)"
          },
          {
            "name": "大争战(11章40-45)"
          },
          {
            "name": "历史大转折：进入末时代(12章)"
          }
        ]
      },
      {
        "name": "启示录思考",
        "playlist": [
          {
            "name": "序言与七教会概论"
          },
          {
            "name": "以弗所、示每拿、别迦摩教会"
          },
          {
            "name": "推雅推喇、撒狄教会"
          },
          {
            "name": "非拉铁非教会"
          },
          {
            "name": "老底嘉教会"
          },
          {
            "name": "七印(4-5章)"
          },
          {
            "name": "七印(6-7章)"
          },
          {
            "name": "七号(8-9章)"
          },
          {
            "name": "七号(10-11章)"
          },
          {
            "name": "第七号(12章)"
          },
          {
            "name": "第七号(13章)"
          },
          {
            "name": "第七号(相关历史)"
          },
          {
            "name": "第七号(14章)"
          },
          {
            "name": "七灾(15-16章)"
          },
          {
            "name": "七灾(17-18章)"
          },
          {
            "name": "从恩典到荣耀(19-22章)"
          }
        ]
      },
      {
        "name": "圣所：福音的唯一蓝图",
        "playlist": [
          {
            "name": "永远的福音与圣所制度"
          },
          {
            "name": "在圣所外院称义的经验：燔祭"
          },
          {
            "name": "在圣所外院称义的经验：赎罪祭"
          },
          {
            "name": "赎愆祭、平安祭和洗濯盆"
          },
          {
            "name": "圣所的第一间：圣化的经验"
          },
          {
            "name": "至圣所：受印的经验"
          },
          {
            "name": "大赎罪日"
          },
          {
            "name": "罪的涂抹"
          },
          {
            "name": "末时代"
          },
          {
            "name": "圣所信息的结论"
          }
        ]
      }
    ]
  },
  {
    "name": "儿童故事",
    "channel": [
      {
        "name": "小燕姐姐讲故事",
        "playlist": []
      }
    ]
  }
]